poodio-0.0.23.dist-info/METADATA
poodio-0.0.23.dist-info/WHEEL
poodio-0.0.23.dist-info/entry_points.txt
poodio-0.0.23.dist-info/licenses/LICENSE.txt
poodio/__init__.pyi
poodio/__init__.py
poodio/poodio.abi3.so
poodio-0.0.23.dist-info/RECORD
