Metadata-Version: 2.4
Name: poodio
Version: 0.0.23
Classifier: Development Status :: 2 - Pre-Alpha
Classifier: Environment :: Console
Classifier: Intended Audience :: Developers
Classifier: License :: OSI Approved :: MIT License
Classifier: Natural Language :: English
Classifier: Operating System :: MacOS
Classifier: Operating System :: Microsoft :: Windows
Classifier: Operating System :: POSIX :: Linux
Classifier: Programming Language :: JavaScript
Classifier: Programming Language :: Python :: 3 :: Only
Classifier: Programming Language :: Python :: 3.10
Classifier: Programming Language :: Python :: 3.11
Classifier: Programming Language :: Python :: 3.12
Classifier: Programming Language :: Python :: 3.13
Classifier: Programming Language :: Python :: 3.14
Classifier: Programming Language :: Python :: 3.8
Classifier: Programming Language :: Python :: 3.9
Classifier: Programming Language :: Python :: Implementation :: CPython
Classifier: Programming Language :: Rust
Classifier: Topic :: Artistic Software
Classifier: Topic :: Games/Entertainment :: Simulation
Classifier: Topic :: Multimedia :: Sound/Audio :: Sound Synthesis
Classifier: Topic :: Software Development :: Libraries
Classifier: Topic :: Utilities
Classifier: Typing :: Typed
License-File: LICENSE.txt
Summary: Farts poo poo audio
Keywords: addon,agent,ai,api,audio,binding,cli,command,easy,executable,fast,fun,funny,joke,library,lightweight,llm,low-latency,mcp,minimal,module,multimedia,music,napi,native,node,performance,poodio,processing,pyo3,python,real-time,rust,script,server,simple,simulation,sound,speed,synthesis,tool,utility
Home-Page: https://github.com/AsherJingkongChen/poopoo/tree/main/poodio#readme
Author: AsherJingkongChen
License: MIT
Requires-Python: >=3.8
Project-URL: documentation, https://docs.rs/poodio
Project-URL: homepage, https://github.com/AsherJingkongChen/poopoo/tree/main/poodio#readme
Project-URL: issues, https://github.com/AsherJingkongChen/poopoo/issues
Project-URL: repository, https://github.com/AsherJingkongChen/poopoo
